AutoTest/FormCommon.py
AutoTest/Zhuru.py
AutoTest/__init__.py
AutoTest/business.py
AutoTest/runtest.py
Auto_Test-0.1.4.dist-info/LICENSE.txt
Auto_Test-0.1.4.dist-info/METADATA
Auto_Test-0.1.4.dist-info/WHEEL
Auto_Test-0.1.4.dist-info/top_level.txt
Auto_Test-0.1.4.dist-info/RECORD
